diffdirs/__init__.py
diffdirs/__main__.py
diffdirs/cli.py
diffdirs/diffdirs.py
diffdirs-0.1.0.dist-info/METADATA
diffdirs-0.1.0.dist-info/RECORD
diffdirs-0.1.0.dist-info/WHEEL
diffdirs-0.1.0.dist-info/entry_points.txt
diffdirs-0.1.0.dist-info/pbr.json
diffdirs-0.1.0.dist-info/top_level.txt
